Workbook

Sheet Read me
A1: The Sourcing Read: working record
A4: What this workbook is
A5: The record of a sourcing read. The AI review and the guided read do the reading; this holds the evidence, the check of the review, the clarification letters, the counts and the register. It is the part that still exists after award, when the chat window does not.
A7: Four rules that are not optional
A8: 1. The weights on tab '1 Weights' are never pasted into the chat. Not in any stage, not in any turn. They live here only.
A9: 2. After each response is read, check five evidence rows at random against the source document and record the result on tab '4 Evidence'. A spot check can expose errors; it cannot establish that the whole table is sound. Before award, check every row the decision rests on.
A10: 3. A refusal is not a silence. A supplier who states plainly what they will not do has given you information. Record it as a declared exclusion.
A11: 4. Use the environment your organisation has approved for bid documents. If you are not sure one exists, practise on the fictional worked example.
A13: How to fill it in
A14: Blue text marks a cell you type in. Black cells are calculated: do not overwrite them.
A15: Yellow cells are the ones that matter most: the sealed weights and the observable line in the register.
A16: The first row of each table is an example, in grey and marked (example). Delete it or type over it.
... A19: It does not rank, price or recommend. It cannot tell you the losing bids were worse: that comparison does not exist. It tells you what you bought, what you did not, and what will never be settled.

Sheet 1 Weights
A1: Weights: sealed before any response is opened
A2: Use only the criteria your request published (in the worked example, request 5.1). Fill this in, date it, and never paste it into the chat. If you have already read the responses, write 'sealed after receipt' in the note and say so in the award file.
A4: Contract | B4: Warehouse and dispatch management system, four sites
A5: Date sealed | B5: 2026-05-04
A6: Sealed by
A7: Note | B7: Sealed before responses opened
A9: Criterion | B9: Weight % | C9: What disqualifies outright
A10: Functional fit | B10: 30 | C10: Any checklist line marked not answered after clarification
A11: Implementation approach | B11: 20
A12: Supplier capability | B12: 25
A13: Total cost over five years | B13: 25
A14: Total, must be 100 | B14: =SUM(B10:B13) | C14: =IF(B14=100,"Sealed total is valid","DOES NOT SUM TO 100")
A16: Changes made after sealing (should be none)
A17: Date | B17: What changed | C17: Who decided it, and why
A18: (example) 2026-06-15 | B18: (example) weight on cost 25% to 30% | C18: (example) delete this row

Sheet 2 Checklist
A1: Checklist coverage
A2: Marked by the guided read against your own request, each mark with a quote. This is the measurement of your document: it has a denominator. The relief list on tab 3 does not, and is a finding rather than a score. Figures shown are the worked example; type over them.
A4: Section | B4: Lines in section | C4: Answered | D4: Partly answered | E4: Not addressed
A5: A What is actually being bought | B5: 6 | C5: 1 | D5: 2 | E5: 3
A6: B Performance and who measures it | B6: 5 | C6: 0 | D6: 2 | E6: 3
A7: C Capacity and peak | B7: 4 | C7: 0 | D7: 1 | E7: 3
A8: D Liability, risk and insurance | B8: 7 | C8: 0 | D8: 2 | E8: 5
A9: E Commercial mechanics | B9: 5 | C9: 0 | D9: 1 | E9: 4
A10: F Data, systems and records | B10: 7 | C10: 0 | D10: 2 | E10: 5
A11: G Continuity and substitution | B11: 5 | C11: 0 | D11: 0 | E11: 5
A12: H Exit | B12: 4 | C12: 0 | D12: 0 | E12: 4
A13: I Governance and audit | B13: 4 | C13: 0 | D13: 1 | E13: 3
A14: TOTAL | B14: =SUM(B5:B13) | C14: =SUM(C5:C13) | D14: =SUM(D5:D13) | E14: =SUM(E5:E13)
A16: =_xlfn.CONCAT("Of ",B14," checklist lines, this document answers ",C14,", partly answers ",D14,", and does not address ",E14,".")

Sheet 3 Relief list
A1: The relief list
A2: Twenty things a capable supplier would be most relieved you did not ask. Run against your own request, before any response is opened. Selected for gaps by construction, so treat the count as a finding, not a score.
A4: # | B4: What a supplier would be relieved you did not ask | C4: Covered? | D4: Clause that covers it | E4: Closed at clarification?
A5: ex | B5: (example) What event starts the dispatch clock and what event stops it | C5: NOT COVERED | E5: Carried as risk
A6: 1
A7: 2
A8: 3
A9: 4
A10: 5
A11: 6
A12: 7
A13: 8
A14: 9
A15: 10
A16: 11
A17: 12
... A25: 20
B27: NOT COVERED | C27: =COUNTIF(C6:C25,"NOT COVERED")

Sheet 4 Evidence
A1: Obligations, terms, exclusions and silences
A2: One row per finding. Every row carries a quote and a reference, or it does not exist. Type the response name exactly as on tab 5. Record any condition or exception from the same clause: a commitment read without its exception is a misreading.
A4: Response | B4: Category | C4: Requirement it concerns | D4: Commitment key | E4: Verbatim quote | F4: Condition or exception | G4: Clause / page | H4: Spot-checked
A5: (example) delete | B5: SILENCE | C5: 48-hour dispatch (request 3.1) | D5: dispatch_48h | E5: Our platform supports high-velocity dispatch operations including same-day and 48-hour dispatch workflows | G5: A2 | H5: Yes - correct
A6: (example) delete | B6: DECLARED EXCLUSION | C6: 48-hour dispatch (request 3.1) | D6: dispatch_48h | E6: Hartlowe makes no commitment as to whether Northvale achieves 48-hour dispatch. | G6: B4 | H6: Yes - correct
A7: (example) delete | B7: OBLIGATION | C7: Dispatch measurement | D7: raw_data_export_free | E7: raw order-level data is exportable in CSV without charge at any time | F7: without charge at any time | G7: B3 | H7: Yes - correct

Sheet 5 Counts
A1: Counts per response
A2: Calculated from tab 4. A count is not a verdict: twenty-seven commitments are not better than nine unless they are the ones your purchase needs. These numbers describe documents; they rank nobody.
A4: Response | B4: Pages | C4: Obligations | D4: Terms | E4: Declared exclusions | F4: Silences | G4: Findings
A5: A Meridian | B5: 94 | C5: =COUNTIFS('4 Evidence'!$A:$A,$A5,'4 Evidence'!$B:$B,"OBLIGATION") | D5: =COUNTIFS('4 Evidence'!$A:$A,$A5,'4 Evidence'!$B:$B,"TERM") | E5: =COUNTIFS('4 Evidence'!$A:$A,$A5,'4 Evidence'!$B:$B,"DECLARED EXCLUSION") | F5: =COUNTIFS('4 Evidence'!$A:$A,$A5,'4 Evidence'!$B:$B,"SILENCE") | G5: =SUM(C5:F5)
A6: B Hartlowe | B6: 41 | C6: =COUNTIFS('4 Evidence'!$A:$A,$A6,'4 Evidence'!$B:$B,"OBLIGATION") | D6: =COUNTIFS('4 Evidence'!$A:$A,$A6,'4 Evidence'!$B:$B,"TERM") | E6: =COUNTIFS('4 Evidence'!$A:$A,$A6,'4 Evidence'!$B:$B,"DECLARED EXCLUSION") | F6: =COUNTIFS('4 Evidence'!$A:$A,$A6,'4 Evidence'!$B:$B,"SILENCE") | G6: =SUM(C6:F6)
A7: C Calderon | B7: 76 | C7: =COUNTIFS('4 Evidence'!$A:$A,$A7,'4 Evidence'!$B:$B,"OBLIGATION") | D7: =COUNTIFS('4 Evidence'!$A:$A,$A7,'4 Evidence'!$B:$B,"TERM") | E7: =COUNTIFS('4 Evidence'!$A:$A,$A7,'4 Evidence'!$B:$B,"DECLARED EXCLUSION") | F7: =COUNTIFS('4 Evidence'!$A:$A,$A7,'4 Evidence'!$B:$B,"SILENCE") | G7: =SUM(C7:F7)
A8: D Pellworth | B8: 58 | C8: =COUNTIFS('4 Evidence'!$A:$A,$A8,'4 Evidence'!$B:$B,"OBLIGATION") | D8: =COUNTIFS('4 Evidence'!$A:$A,$A8,'4 Evidence'!$B:$B,"TERM") | E8: =COUNTIFS('4 Evidence'!$A:$A,$A8,'4 Evidence'!$B:$B,"DECLARED EXCLUSION") | F8: =COUNTIFS('4 Evidence'!$A:$A,$A8,'4 Evidence'!$B:$B,"SILENCE") | G8: =SUM(C8:F8)
A9: TOTAL | C9: =SUM(C5:C8) | D9: =SUM(D5:D8) | E9: =SUM(E5:E8) | F9: =SUM(F5:F8) | G9: =SUM(G5:G8)
A11: Read order. Record it: first-read anchoring is the strongest distortion after the weights
A12: A, B, C, D as received

Sheet 6 Differences
A1: The difference pass
A2: Obligations only, one row per commitment key. A commitment every response makes is not a difference; one some make and others do not is. Split a key wherever scope, conditions or exceptions differ. The count depends on the grouping: treat it as a map of where to look, not as a finding.
A4: # | B4: The real difference | C4: Carried by | D4: Clause
A5: ex | B5: (example) Elapsed dispatch time reported per order line, from day one | C5: B | D5: B2, B3
A6: 1
A7: 2
A8: 3
A9: 4
A10: 5
A11: 6
A12: 7
A13: 8
A14: 9
A15: 10
A16: 11
A17: 12
... A65: 60
B67: REAL DIFFERENCES | C67: =COUNTA(B6:B65)

Sheet 7 Register
A1: The register
A2: Filled on the day you award. For each claim that decided it, write what you would see if it held, when, and on which record you control. For each claim you can check, write your odds that it holds: start from how often projects like this slip, then list what in the contract would cause it to fail. The odds are yours, never the chat's. It cannot tell you the losing bids were worse: that comparison does not exist. It tells you whether the claims that won the work were true.
A4: Award date | B4: 2026-07-01
A6: Claim that decided the award | B6: Clause | C6: What you would observe if it held | D6: When | E6: Record it comes from, one YOU control | F6: Checkable? | G6: Your odds it holds, % | H6: Verdict | I6: Forecast error
A7: (example) Supports 48-hour dispatch workflows | B7: A2 | C7: Only that dispatch workflows exist. Nothing would show whether they meet the 48-hour commitment. | D7: None | E7: None | F7: NO - nothing would settle it | H7: CANNOT BE CHECKED
I8: =IF(OR(G8="",H8=""),"",IF(H8="HELD",(G8/100-1)^2,IF(H8="DID NOT HOLD",(G8/100)^2,"")))
I9: =IF(OR(G9="",H9=""),"",IF(H9="HELD",(G9/100-1)^2,IF(H9="DID NOT HOLD",(G9/100)^2,"")))
I10: =IF(OR(G10="",H10=""),"",IF(H10="HELD",(G10/100-1)^2,IF(H10="DID NOT HOLD",(G10/100)^2,"")))
I11: =IF(OR(G11="",H11=""),"",IF(H11="HELD",(G11/100-1)^2,IF(H11="DID NOT HOLD",(G11/100)^2,"")))
I12: =IF(OR(G12="",H12=""),"",IF(H12="HELD",(G12/100-1)^2,IF(H12="DID NOT HOLD",(G12/100)^2,"")))
I13: =IF(OR(G13="",H13=""),"",IF(H13="HELD",(G13/100-1)^2,IF(H13="DID NOT HOLD",(G13/100)^2,"")))
I14: =IF(OR(G14="",H14=""),"",IF(H14="HELD",(G14/100-1)^2,IF(H14="DID NOT HOLD",(G14/100)^2,"")))
I15: =IF(OR(G15="",H15=""),"",IF(H15="HELD",(G15/100-1)^2,IF(H15="DID NOT HOLD",(G15/100)^2,"")))
I16: =IF(OR(G16="",H16=""),"",IF(H16="HELD",(G16/100-1)^2,IF(H16="DID NOT HOLD",(G16/100)^2,"")))
I17: =IF(OR(G17="",H17=""),"",IF(H17="HELD",(G17/100-1)^2,IF(H17="DID NOT HOLD",(G17/100)^2,"")))
I18: =IF(OR(G18="",H18=""),"",IF(H18="HELD",(G18/100-1)^2,IF(H18="DID NOT HOLD",(G18/100)^2,"")))
I19: =IF(OR(G19="",H19=""),"",IF(H19="HELD",(G19/100-1)^2,IF(H19="DID NOT HOLD",(G19/100)^2,"")))
A21: CLAIMS THAT CANNOT BE CHECKED | B21: =COUNTIF(F8:F19,"NO*")
A22: AVERAGE FORECAST ERROR (0 is perfect, 1 is as wrong as possible) | B22: =IFERROR(AVERAGE(I8:I19),"")
A23: What to ask for next time, generated from every row above that cannot be checked

Sheet 8 Award note
A1: The award note
A2: Four counts for the top of the note, then what must be written into the contract. The counts describe the documents and the claims; they rank nobody.
A4: Reliefs not covered | B4: ='3 Relief list'!C27
A5: Silences | B5: ='5 Counts'!F9
A6: Real differences | B6: ='6 Differences'!C67
A7: Claims that cannot be checked | B7: ='7 Register'!B21
A9: Copy this line into the award note
A10: =_xlfn.CONCAT("Reliefs not covered: ",B4," · Silences: ",B5," · Real differences: ",B6," · Claims that cannot be checked: ",B7)
A12: Checklist coverage
A13: ='2 Checklist'!A16
A15: What must be written into the contract. Name where each obligation that decided the award must appear. Do not state that anything is enforceable: that is for the people who draft and sign the agreement.
A16: Obligation that decided the award | B16: Clause | C16: Where it must appear in the signed agreement
A17: (example) Elapsed dispatch time reported per order line, from each site go-live | B17: B2, B3 | C17: (example) Service description, reporting schedule

Sheet 9 Review check
A1: Checking the AI review
A2: Run /vendor-review (or any AI summary) first. Then check every statement your decision will rest on against the bid's own words. The recommendation is recorded as made; it is not evidence.
A4: What the review says | B4: Clause | C4: What the bid says, word for word | D4: Verdict | E4: Checked by, date
A5: (example) Lead and two seniors named in contract and locked | B5: B25 | C5: (example) will not replace them without Northvale's written agreement except on termination of employment | D5: DROPS A CONDITION
A6: (example) Negotiate (preferred) | D6: RECOMMENDATION
A48: DROPS A CONDITION or OVERSTATES | B48: =COUNTIF(D7:D46,"DROPS A CONDITION")+COUNTIF(D7:D46,"OVERSTATES")

Sheet 10 Clarifications
A1: The clarification letters
A2: Every silence in a response becomes one question, citing the sentence it answers and asking for a commitment in writing: what, by when, measured how. Where no answer could settle it, give the reason instead.
A4: Supplier | B4: Clause | C4: What they wrote, word for word | D4: Question, or the reason for none | E4: Answer received | F4: Closed?
A5: (example) A Meridian | B5: A16 | C5: Performance measurement against dispatch commitments is fully supported | D5: Is dispatch performance measurement a standard report at go-live, or something built with the report builder, and is it in the price?
A107: STILL OPEN | B107: =COUNTIF(F6:F105,"Still open")
